{
    "tables": [
      {
        "name": "events",
        "displayName": "User Events",
        "description": "All user interaction events",
        "schema": "public",
        "type": "table",
        "rowCount": 10000,
        "category": "Analytics",
        "explorable": true,
        "refreshedAt": "2025-04-01T12:00:00Z",
        "columns": ["id", "timestamp", "user_id", "event_type", "page", "properties"]
      },
      {
        "name": "users",
        "displayName": "Users",
        "description": "Registered users",
        "schema": "public",
        "type": "table",
        "rowCount": 5000,
        "category": "Core",
        "explorable": true,
        "refreshedAt": "2025-04-01T12:00:00Z",
        "columns": ["id", "name", "email", "created_at", "country", "status"]
      },
      {
        "name": "products",
        "displayName": "Products",
        "description": "Available products",
        "schema": "public",
        "type": "table",
        "rowCount": 200,
        "category": "Core",
        "explorable": true,
        "refreshedAt": "2025-04-01T12:00:00Z",
        "columns": ["id", "name", "price", "category", "created_at"]
      }
    ],
    "columns": [
      {
        "name": "id",
        "tableName": "events",
        "displayName": "ID",
        "description": "Unique identifier",
        "dataType": "integer",
        "nullable": false,
        "primaryKey": true,
        "explorable": true
      },
      {
        "name": "timestamp",
        "tableName": "events",
        "displayName": "Time",
        "description": "When the event occurred",
        "dataType": "timestamp",
        "nullable": false,
        "primaryKey": false,
        "explorable": true
      },
      {
        "name": "user_id",
        "tableName": "events",
        "displayName": "User",
        "description": "User who triggered the event",
        "dataType": "integer",
        "nullable": true,
        "primaryKey": false,
        "foreignKey": "users.id",
        "explorable": true
      },
      {
        "name": "event_type",
        "tableName": "events",
        "displayName": "Event Type",
        "description": "Type of event",
        "dataType": "string",
        "nullable": false,
        "primaryKey": false,
        "explorable": true
      },
      {
        "name": "page",
        "tableName": "events",
        "displayName": "Page",
        "description": "Page where the event occurred",
        "dataType": "string",
        "nullable": true,
        "primaryKey": false,
        "explorable": true
      },
      {
        "name": "properties",
        "tableName": "events",
        "displayName": "Properties",
        "description": "Event properties",
        "dataType": "json",
        "nullable": true,
        "primaryKey": false,
        "explorable": false
      },
      {
        "name": "id",
        "tableName": "users",
        "displayName": "ID",
        "description": "Unique identifier",
        "dataType": "integer",
        "nullable": false,
        "primaryKey": true,
        "explorable": true
      },
      {
        "name": "name",
        "tableName": "users",
        "displayName": "Name",
        "description": "User's full name",
        "dataType": "string",
        "nullable": false,
        "primaryKey": false,
        "explorable": true
      },
      {
        "name": "email",
        "tableName": "users",
        "displayName": "Email",
        "description": "User's email address",
        "dataType": "string",
        "nullable": false,
        "primaryKey": false,
        "explorable": true
      },
      {
        "name": "created_at",
        "tableName": "users",
        "displayName": "Joined",
        "description": "When the user registered",
        "dataType": "timestamp",
        "nullable": false,
        "primaryKey": false,
        "explorable": true
      },
      {
        "name": "country",
        "tableName": "users",
        "displayName": "Country",
        "description": "User's country",
        "dataType": "string",
        "nullable": true,
        "primaryKey": false,
        "explorable": true
      },
      {
        "name": "status",
        "tableName": "users",
        "displayName": "Status",
        "description": "Account status",
        "dataType": "string",
        "nullable": false,
        "primaryKey": false,
        "explorable": true
      }
    ],
    "relationships": [
      {
        "sourceTable": "events",
        "sourceColumn": "user_id",
        "targetTable": "users",
        "targetColumn": "id",
        "relationship": "many-to-one",
        "displayName": "User",
        "automatic": true
      }
    ]
  }